wes/__init__.py
wes/_lib.py
wes-0.1.4.dist-info/DESCRIPTION.rst
wes-0.1.4.dist-info/METADATA
wes-0.1.4.dist-info/RECORD
wes-0.1.4.dist-info/WHEEL
wes-0.1.4.dist-info/metadata.json
wes-0.1.4.dist-info/top_level.txt
